u8timeseries/__init__.py
u8timeseries/timeseries.py
u8timeseries/backtesting/__init__.py
u8timeseries/backtesting/backtesting_udf.py
u8timeseries/backtesting/forecasting_simulation.py
u8timeseries/metrics/__init__.py
u8timeseries/metrics/metrics.py
u8timeseries/models/__init__.py
u8timeseries/models/arima.py
u8timeseries/models/autoregressive_model.py
u8timeseries/models/baselines.py
u8timeseries/models/exponential_smoothing.py
u8timeseries/models/prophet.py
u8timeseries/models/regressive_model.py
u8timeseries/models/sequential_aggregation.py
u8timeseries/models/standard_regressive_model.py
u8timeseries/models/statistics.py
u8timeseries/models/theta.py
u8timeseries/tests/__init__.py
u8timeseries/tests/test_autoregression_models.py
u8timeseries/tests/test_metrics.py
u8timeseries/tests/test_missing_values.py
u8timeseries/tests/test_regression_models.py
u8timeseries/tests/test_statistics.py
u8timeseries/tests/test_timeseries.py
u8timeseries/tests/test_timeseries_generation.py
u8timeseries/utils/__init__.py
u8timeseries/utils/missing_values.py
u8timeseries/utils/timeseries_generation.py
u8timeseries/utils/types.py
u8timeseries/utils/utils.py
u8timeseries-0.0.2.dist-info/LICENSE
u8timeseries-0.0.2.dist-info/METADATA
u8timeseries-0.0.2.dist-info/WHEEL
u8timeseries-0.0.2.dist-info/top_level.txt
u8timeseries-0.0.2.dist-info/RECORD
