Metadata-Version: 2.1
Name: u8timeseries
Version: 0.0.2
Summary: A collection of easy-to-use timeseries forecasting models
Home-page: http://github.com/unit8co/u8timeseries
Author: Unit8 SA
Author-email: info@unit8.co
License: Apache License 2.0
Platform: UNKNOWN
Requires-Python: >=3.6
Requires-Dist: numpy (>=1.18.2)
Requires-Dist: dateutils (>=0.6.8)
Requires-Dist: scipy (>=1.4.1)
Requires-Dist: statsmodels (>=0.11.1)
Requires-Dist: pmdarima (>=1.5.3)
Requires-Dist: plotly (>=4.6.0)
Requires-Dist: matplotlib (>=3.2.1)
Requires-Dist: fbprophet (>=0.5)
Requires-Dist: scikit-learn (>=0.21.2)
Requires-Dist: pandas (>=0.23.1)
Requires-Dist: tqdm (>=4.32.1)
Requires-Dist: ipywidgets
